indieweb_rocks/__init__.py
indieweb_rocks/__web__.py
indieweb_rocks/static/cc/by.svg
indieweb_rocks/static/cc/cc.svg
indieweb_rocks/static/cc/nc-eu.svg
indieweb_rocks/static/cc/nc-jp.svg
indieweb_rocks/static/cc/nc.svg
indieweb_rocks/static/cc/nd.svg
indieweb_rocks/static/cc/pd.svg
indieweb_rocks/static/cc/remix.svg
indieweb_rocks/static/cc/sa.svg
indieweb_rocks/static/cc/sampling.plus.svg
indieweb_rocks/static/cc/sampling.svg
indieweb_rocks/static/cc/share.svg
indieweb_rocks/static/cc/zero.svg
indieweb_rocks/static/favicon.ico
indieweb_rocks/static/microformats.png
indieweb_rocks/static/screen.css
indieweb_rocks/templates/__init__.py
indieweb_rocks/templates/a11y.html
indieweb_rocks/templates/categories.html
indieweb_rocks/templates/commons.html
indieweb_rocks/templates/crawl_enqueued.html
indieweb_rocks/templates/crawler.html
indieweb_rocks/templates/domain_suffix_does_not_exist.html
indieweb_rocks/templates/faq.html
indieweb_rocks/templates/featured.html
indieweb_rocks/templates/features.html
indieweb_rocks/templates/indieauth.html
indieweb_rocks/templates/landing.html
indieweb_rocks/templates/map.html
indieweb_rocks/templates/page.html
indieweb_rocks/templates/people.html
indieweb_rocks/templates/posts.html
indieweb_rocks/templates/privacy.html
indieweb_rocks/templates/results.html
indieweb_rocks/templates/screens.html
indieweb_rocks/templates/silo.html
indieweb_rocks/templates/silos.html
indieweb_rocks/templates/site.html
indieweb_rocks/templates/site_not_responding.html
indieweb_rocks/templates/sites.html
indieweb_rocks/templates/stats.html
indieweb_rocks/templates/template.html
indieweb_rocks/templates/terms.html
indieweb_rocks/templates/the_street.html
indieweb_rocks/templates/toolbox/representative_card.html
indieweb_rocks/templates/toolbox/representative_feed.html
indieweb_rocks/utils.py
indieweb_rocks-0.0.7.dist-info/METADATA
indieweb_rocks-0.0.7.dist-info/entry_points.txt
indieweb_rocks-0.0.7.dist-info/WHEEL
indieweb_rocks-0.0.7.dist-info/RECORD
