Metadata-Version: 2.1
Name: indieweb-rocks
Version: 0.0.7
Summary: IndieWeb validator
License: 0BSD
Author: Angelo Gladding
Author-email: angelo@ragt.ag
Requires-Python: >=3.10,<3.11
Classifier: License :: Other/Proprietary License
Classifier: Programming Language :: Python :: 3
Classifier: Programming Language :: Python :: 3.10
Requires-Dist: micropub (>=0.0)
Requires-Dist: phonenumbers (>=8.12.55,<9.0.0)
Requires-Dist: python-whois (>=0.8.0,<0.9.0)
Requires-Dist: svglib (>=1.3.0,<2.0.0)
Requires-Dist: typesense (>=0.18.0,<0.19.0)
Requires-Dist: webint (>=0.0)
Requires-Dist: webint-data (>=0.0)
Requires-Dist: webint-guests (>=0.0)
Requires-Dist: webint-owner (>=0.0)
Requires-Dist: webint-system (>=0.0)
